[{
  "_id": {
    "$oid": "6467dd25d249ee11f4021944"
  },
  "thumbUrl": "images/exercises/quads/1.jpg",
  "postLink": "",
  "category": "Fitness",
  "categoryLink": "",
  "title": "Chest Workout",
  "summary": "This is a summary of the chest workout.",
  "author": "Tony",
  "datePublished": "20",
  "__v": 0
},{
  "_id": {
    "$oid": "6467dd25d249ee11f402195b"
  },
  "thumbUrl": "images/exercises/quads/2.jpg",
  "postLink": "",
  "category": "Fitness",
  "categoryLink": "",
  "title": "Chest Workout",
  "summary": "This is a summary of the chest workout.",
  "author": "Tony",
  "datePublished": "20",
  "__v": 0
},{
  "_id": {
    "$oid": "6467dd25d249ee11f402196d"
  },
  "thumbUrl": "images/exercises/quads/3.jpg",
  "postLink": "",
  "category": "Fitness",
  "categoryLink": "",
  "title": "Chest Workout",
  "summary": "This is a summary of the chest workout.",
  "author": "Tony",
  "datePublished": "20",
  "__v": 0
},{
  "_id": {
    "$oid": "6467dd25d249ee11f402197f"
  },
  "thumbUrl": "images/exercises/quads/4.jpg",
  "postLink": "",
  "category": "Fitness",
  "categoryLink": "",
  "title": "Chest Workout",
  "summary": "This is a summary of the chest workout.",
  "author": "Tony",
  "datePublished": "20",
  "__v": 0
},{
  "_id": {
    "$oid": "6467dd25d249ee11f4021995"
  },
  "thumbUrl": "images/exercises/quads/5.jpg",
  "postLink": "",
  "category": "Fitness",
  "categoryLink": "",
  "title": "Chest Workout",
  "summary": "This is a summary of the chest workout.",
  "author": "Tony",
  "datePublished": "20",
  "__v": 0
}]